elastictabstops/__init__.py
elastictabstops/classes.py
elastictabstops/convert.py
elastictabstops/tests.py
ElasticTabstops-1.0.1.dist-info/LICENCE.txt
ElasticTabstops-1.0.1.dist-info/METADATA
ElasticTabstops-1.0.1.dist-info/WHEEL
ElasticTabstops-1.0.1.dist-info/top_level.txt
ElasticTabstops-1.0.1.dist-info/RECORD
