Metadata-Version: 2.1
Name: ElasticTabstops
Version: 1.0.1
Summary: Converts text indented/aligned with elastic tabstops
Home-page: https://github.com/nickgravgaard/elastic-tabstops-py
Author: Nick Gravgaard
Author-email: nick@nickgravgaard.com
License: MIT/X11
Classifier: License :: OSI Approved :: MIT License
Classifier: Programming Language :: Python :: 2.7
Classifier: Programming Language :: Python :: 3
Classifier: Topic :: Text Processing
Classifier: Topic :: Text Processing :: Filters
Classifier: Topic :: Text Processing :: General
Classifier: Topic :: Text Processing :: Markup
License-File: LICENCE.txt
